BoschSapWebGuiAutomation/__init__.py
BoschSapWebGuiAutomation/common_config.py
BoschSapWebGuiAutomation/common_functions.py
BoschSapWebGuiAutomation/data_process_functions.py
BoschSapWebGuiAutomation/helper_functions.py
BoschSapWebGuiAutomation/t_code_functions.py
BoschSapWebGuiAutomation-0.2.37.dist-info/LICENSE
BoschSapWebGuiAutomation-0.2.37.dist-info/METADATA
BoschSapWebGuiAutomation-0.2.37.dist-info/WHEEL
BoschSapWebGuiAutomation-0.2.37.dist-info/top_level.txt
BoschSapWebGuiAutomation-0.2.37.dist-info/RECORD
