Metadata-Version: 2.1
Name: BoschSapWebGuiAutomation
Version: 0.2.37
Summary: This package is used for building common automation functions for sap web gui within Bosch
Author-email: LV Zhichao <zhichao.lv@cn.bosch.com>
Project-URL: Homepage, https://github.boschdevcloud.com/LZV2SZH/SapWebGuiAutomation
Project-URL: Bug Tracker, https://github.boschdevcloud.com/LZV2SZH/SapWebGuiAutomation/issues
Classifier: Programming Language :: Python :: 3
Classifier: Operating System :: OS Independent
Classifier: License :: OSI Approved :: MIT License
Requires-Python: >=3.7
License-File: LICENSE
Requires-Dist: pyperclip
Requires-Dist: pysmb
Requires-Dist: selenium==4.8.0
